Metadata-Version: 1.1
Name: gppeval
Version: 2020.10.1.0.2.dev1
Summary: Geothermal Power Potential assessment
Home-page: https://github.com/cpocasangre/gppeval
Author: Carlos O. POCASANGRE JIMENEZ
Author-email: carlos.pocasangre@fia.ues.edu.sv
License: MIT License
Keywords: monte carlo latin hypercube geothermal power potential volumetric method geothermal reservoir
Platform: UNKNOWN
Classifier: Development Status :: 2 - Pre-Alpha
Classifier: License :: OSI Approved :: MIT License
Classifier: Programming Language :: Python :: 2.7
Classifier: Programming Language :: Python :: 3.8
